hello_dj_26-0.1.0.dist-info/METADATA
hello_dj_26-0.1.0.dist-info/WHEEL
hello_dj_26/__init__.py
hello_dj_26-0.1.0.dist-info/RECORD
