Metadata-Version: 2.1
Name: hello-dj-26
Version: 0.1.0
Summary: hello dj26 first pypi
Author-Email: pysatellite <pysatellite@gmail.com>
License: MIT
Requires-Python: >=3.8
